stMMR/__init__.py
stMMR/layers.py
stMMR/models.py
stMMR/process.py
stMMR/train_model.py
stMMR/utils.py
stMMR-1.0.1.dist-info/LICENSE
stMMR-1.0.1.dist-info/METADATA
stMMR-1.0.1.dist-info/WHEEL
stMMR-1.0.1.dist-info/top_level.txt
stMMR-1.0.1.dist-info/RECORD
