Metadata-Version: 2.1
Name: stMMR
Version: 1.0.1
Summary: stMMR: Multi-Modal Feature Representation in Spatial Transcriptomics with Similarity Contrastive Learning
Author-email: zhang_daoliang <649135593@qq.com>
License: MIT License
Project-URL: Home, https://github.com/nayu0419/stMMR
Classifier: License :: OSI Approved :: MIT License
License-File: LICENSE
